requests_websub_auth/__init__.py
requests_websub_auth-0.0.5.dist-info/LICENSE
requests_websub_auth-0.0.5.dist-info/METADATA
requests_websub_auth-0.0.5.dist-info/WHEEL
requests_websub_auth-0.0.5.dist-info/top_level.txt
requests_websub_auth-0.0.5.dist-info/RECORD
