Metadata-Version: 2.1
Name: requests-websub-auth
Version: 0.0.5
Summary: Implements WebSub X-Hub-Signature authentication for the Python Requests library
Home-page: https://github.com/QuiNovas/requests-websub-auth
Author: Joseph Wortmann
Author-email: jwortmann@quinovas.com
License: Apache 2.0
Keywords: requests websub x-hub-signature
Classifier: Development Status :: 4 - Beta
Classifier: Intended Audience :: Developers
Classifier: License :: OSI Approved :: Apache Software License
Classifier: Programming Language :: Python :: 3.9
Requires-Python: >=3.9
License-File: LICENSE
Requires-Dist: requests
